searchstringparser/__init__.py
searchstringparser/lexer/__init__.py
searchstringparser/lexer/general.py
searchstringparser/parser/__init__.py
searchstringparser/parser/postgresql.py
searchstringparser-0.3.0.dist-info/AUTHORS.rst
searchstringparser-0.3.0.dist-info/LICENSE.rst
searchstringparser-0.3.0.dist-info/METADATA
searchstringparser-0.3.0.dist-info/WHEEL
searchstringparser-0.3.0.dist-info/top_level.txt
searchstringparser-0.3.0.dist-info/RECORD
