Metadata-Version: 2.1
Name: searchstringparser
Version: 0.3.0
Summary: Parse a more general search syntax to conform with a particular SQL dialect.
Home-page: https://github.com/AGHerwig/searchstringparser
Author: Moritz Emanuel Beber
Author-email: beber@molgen.mpg.de
License: BSD
Keywords: SQL,PostgreSQL,search,parser
Platform: UNKNOWN
Classifier: Development Status :: 5 - Production/Stable
Classifier: Intended Audience :: Developers
Classifier: License :: OSI Approved :: BSD License
Classifier: Natural Language :: English
Classifier: Operating System :: Microsoft :: Windows
Classifier: Operating System :: POSIX
Classifier: Operating System :: Unix
Classifier: Programming Language :: Python
Classifier: Programming Language :: Python :: 2.7
Classifier: Programming Language :: Python :: 3
Classifier: Programming Language :: Python :: 3.5
Classifier: Programming Language :: Python :: 3.6
Classifier: Programming Language :: Python :: 3.7
Classifier: Programming Language :: Python :: Implementation :: CPython
Classifier: Topic :: Database :: Front-Ends
Requires-Dist: ply
